test_CLlmGenJson.py
test_LlmGenJson.py
LlmGenJson/CLlmGenJson.py
LlmGenJson/LlmGenJson.py
LlmGenJson/__init__.py
LlmGenJson/funcHigherVer.py
LlmGenJson/wyf_strict_json.py
llmgenjson-0.1.6.dist-info/METADATA
llmgenjson-0.1.6.dist-info/WHEEL
llmgenjson-0.1.6.dist-info/top_level.txt
llmgenjson-0.1.6.dist-info/RECORD
