Metadata-Version: 2.4
Name: LlmGenJson
Version: 0.1.6
Summary: Generate JSON data using LLM
Requires-Python: >=3.10
Requires-Dist: openai>=1.82.0
Requires-Dist: python-dotenv>=1.1.0
Requires-Dist: weberfuncs>=0.0.171
